{
  "updated_at": "2026-07-16T06:55:56.980358+02:00",
  "model_version": "48d62c0",
  "physics2_rev": 1,
  "params": {
    "cp_shelter_front": 0.5477894706069018,
    "cp_shelter_back": 0.5229632805939874,
    "vent_eff": 0.4491365463625222,
    "q_moist": 0.80322962468143,
    "stair_exch": 3.25,
    "living": {
      "c_air": 1.9120083844951965,
      "c_fast": 0.7535491462765402,
      "c_deep": 1.9692634849827635,
      "h_af": 0.5339857351929439,
      "h_fd": 2.196664932554942,
      "ua_env": 1.0887427408699786,
      "solar_gain": 0.43797585491170293,
      "ua_party": 0.9959667089691806,
      "q_int": 0.3296758877625145,
      "ua_roof": 1.0,
      "f_air": 0.22778540122623353,
      "w_buf": 0.5026851832321672
    },
    "ted": {
      "c_air": 1.153347943364927,
      "c_fast": 1.7190541444068843,
      "c_deep": 1.9707931552977804,
      "h_af": 0.5081526874340777,
      "h_fd": 0.5900647890443658,
      "ua_env": 0.43445355941619523,
      "solar_gain": 0.4375,
      "ua_party": 0.5750746557528026,
      "q_int": 0.31168466335005635,
      "ua_roof": 1.0,
      "f_air": 0.45088920933296717,
      "w_buf": 0.5997564752870728
    },
    "hotties": {
      "c_air": 1.5333306136169331,
      "c_fast": 2.822497710652611,
      "c_deep": 3.1383894814872906,
      "h_af": 2.5127133941804436,
      "h_fd": 0.6107175081787652,
      "ua_env": 0.9163919044363188,
      "solar_gain": 0.4375,
      "ua_party": 0.8188848576284751,
      "q_int": 0.9296522646075152,
      "ua_roof": 1.0,
      "f_air": 0.3594412825770913,
      "w_buf": 0.9926033254282531
    },
    "office": {
      "c_air": 1.0599895094155576,
      "c_fast": 1.7097960762977085,
      "c_deep": 0.4030409076150733,
      "h_af": 3.8143585788131484,
      "h_fd": 0.7525281048058521,
      "ua_env": 0.7691952937421451,
      "solar_gain": 0.794249808817214,
      "ua_party": 0.8008351057004722,
      "q_int": 0.47696233338168315,
      "ua_roof": 0.25809743589416095,
      "f_air": 0.175,
      "w_buf": 0.617288768670053
    },
    "stair": {
      "c_air": 1.0,
      "c_fast": 1.0,
      "c_deep": 1.0,
      "h_af": 1.0,
      "h_fd": 1.0,
      "ua_env": 1.0,
      "solar_gain": 1.0,
      "ua_party": 1.0,
      "q_int": 1.0,
      "ua_roof": 1.0,
      "f_air": 0.4,
      "w_buf": 1.0
    },
    "bath": {
      "c_air": 0.475,
      "c_fast": 2.4347031501013126,
      "c_deep": 3.006374450528014,
      "h_af": 0.6263440868252149,
      "h_fd": 1.2257092512564238,
      "ua_env": 0.4447735407182361,
      "solar_gain": 1.0,
      "ua_party": 0.5025782477414372,
      "q_int": 0.2708179227138072,
      "ua_roof": 1.0,
      "f_air": 0.4,
      "w_buf": 1.8812205692543853
    }
  },
  "rmse": 2.022,
  "rmse_rh": 11.02,
  "railed": [],
  "anchor_at": "2026-07-16T05:45:54.026461+02:00",
  "anchor_src": "095d499",
  "rmse_history": [
    {
      "t": "2026-07-16T06:55:56.980358+02:00",
      "rmse": 2.022,
      "held": false,
      "paused": false,
      "version": "48d62c0",
      "rmse_rh": 11.02,
      "skill": 0.168,
      "rmse_naive": 2.43,
      "wx": {
        "tmax": 31.2,
        "solar_peak": 864,
        "solar_mean": 326
      },
      "anchored": true
    }
  ]
}