{"generated_at":"2026-05-28T18:50:42.565851Z","source":"Wunderground IUTREC165 (36d) + Open-Meteo solar","wu_days":36,"soil":{"FC":0.2,"WP":0.09},"zones":{"lawn":{"name":"Lawn","Zr":0.2},"shrubs":{"name":"Shrubs","Zr":0.5}},"irrigation_rates":{"lawn":0.3333333333333333,"shrubs":0.03333333333333333},"location":{"lat":52.0907,"lon":5.1214,"name":"Utrecht Oost"},"seed_source":"previous_run","theta_end":{"as_of":"2026-05-28","lawn":0.179,"shrubs":0.193},"days":[{"date":"2026-04-23","Tmax":18.2,"Tmin":5.1,"Tmean":10.9,"RHmean":66.3,"u2":0.0,"Rs":null,"precip":0.0,"ET0_om":null,"precip_prob":0,"era5_theta_lawn":null,"era5_theta_shrubs":null,"forecast":false,"partial_factor":1.0,"hasWU":true,"ET0":3.5514814814814826,"lawn_theta":0.128,"lawn_depletion":65.5,"lawn_ETc":2.52,"lawn_Kc":0.709,"lawn_irrigation":0,"lawn_drainage":0.0,"lawn_interception":0.0,"lawn_Kcb":0.847,"lawn_Ke":0.06,"lawn_E":0.21,"lawn_T":2.31,"lawn_De":8.21,"lawn_few":0.05,"shrubs_theta":0.1936,"shrubs_depletion":5.8,"shrubs_ETc":3.01,"shrubs_Kc":0.847,"shrubs_irrigation":0,"shrubs_drainage":0.0,"shrubs_interception":0.0,"shrubs_Kcb":0.727,"shrubs_Ke":0.12,"shrubs_E":0.43,"shrubs_T":2.58,"shrubs_De":8.43,"shrubs_few":0.1},{"date":"2026-04-24","Tmax":17.5,"Tmin":6.3,"Tmean":10.9,"RHmean":73.7,"u2":0.0,"Rs":null,"precip":0.0,"ET0_om":null,"precip_prob":0,"era5_theta_lawn":null,"era5_theta_shrubs":null,"forecast":false,"partial_factor":1.0,"hasWU":true,"ET0":3.5514814814814826,"lawn_theta":0.1183,"lawn_depletion":74.3,"lawn_ETc":1.95,"lawn_Kc":0.548,"lawn_irrigation":0,"lawn_drainage":0.0,"lawn_interception":0.0,"lawn_Kcb":0.848,"lawn_Ke":0.06,"lawn_E":0.21,"lawn_T":1.73,"lawn_De":8.43,"lawn_few":0.05,"shrubs_theta":0.1876,"shrubs_depletion":11.3,"shrubs_ETc":3.01,"shrubs_Kc":0.848,"shrubs_irrigation":0,"shrubs_drainage":0.0,"shrubs_interception":0.0,"shrubs_Kcb":0.728,"shrubs_Ke":0.12,"shrubs_E":0.43,"shrubs_T":2.59,"shrubs_De":8.85,"shrubs_few":0.1},{"date":"2026-04-25","Tmax":21.0,"Tmin":4.1,"Tmean":11.2,"RHmean":65.9,"u2":0.0,"Rs":null,"precip":0.0,"ET0_om":null,"precip_prob":0,"era5_theta_lawn":null,"era5_theta_shrubs":null,"forecast":false,"partial_factor":1.0,"hasWU":true,"ET0":3.551481481481483,"lawn_theta":0.1272,"lawn_depletion":66.1,"lawn_ETc":1.51,"lawn_Kc":0.424,"lawn_irrigation":3.3,"lawn_drainage":0.0,"lawn_interception":0.0,"lawn_Kcb":0.85,"lawn_Ke":0.06,"lawn_E":0.21,"lawn_T":1.29,"lawn_De":5.34,"lawn_few":0.05,"shrubs_theta":0.1815,"shrubs_depletion":16.8,"shrubs_ETc":3.02,"shrubs_Kc":0.85,"shrubs_irrigation":0,"shrubs_drainage":0.0,"shrubs_interception":0.0,"shrubs_Kcb":0.73,"shrubs_Ke":0.12,"shrubs_E":0.43,"shrubs_T":2.59,"shrubs_De":9.28,"shrubs_few":0.1},{"date":"2026-04-26","Tmax":18.8,"Tmin":5.1,"Tmean":11.2,"RHmean":64.5,"u2":0.0,"Rs":null,"precip":0.0,"ET0_om":null,"precip_prob":0,"era5_theta_lawn":null,"era5_theta_shrubs":null,"forecast":false,"partial_factor":1.0,"hasWU":true,"ET0":3.5514814814814826,"lawn_theta":0.1341,"lawn_depletion":59.9,"lawn_ETc":1.92,"lawn_Kc":0.541,"lawn_irrigation":3.3,"lawn_drainage":0.0,"lawn_interception":0.0,"lawn_Kcb":0.852,"lawn_Ke":0.06,"lawn_E":0.21,"lawn_T":1.71,"lawn_De":2.25,"lawn_few":0.05,"shrubs_theta":0.1761,"shrubs_depletion":21.8,"shrubs_ETc":3.03,"shrubs_Kc":0.852,"shrubs_irrigation":0.3,"shrubs_drainage":0.0,"shrubs_interception":0.0,"shrubs_Kcb":0.732,"shrubs_Ke":0.12,"shrubs_E":0.43,"shrubs_T":2.6,"shrubs_De":9.4,"shrubs_few":0.1},{"date":"2026-04-27","Tmax":19.0,"Tmin":4.4,"Tmean":11.3,"RHmean":63.3,"u2":0.0,"Rs":null,"precip":0.0,"ET0_om":null,"precip_prob":0,"era5_theta_lawn":null,"era5_theta_shrubs":null,"forecast":false,"partial_factor":1.0,"hasWU":true,"ET0":3.551481481481483,"lawn_theta":0.1229,"lawn_depletion":70.1,"lawn_ETc":2.24,"lawn_Kc":0.63,"lawn_irrigation":0,"lawn_drainage":0.0,"lawn_interception":0.0,"lawn_Kcb":0.853,"lawn_Ke":0.06,"lawn_E":0.21,"lawn_T":2.03,"lawn_De":2.47,"lawn_few":0.05,"shrubs_theta":0.17,"shrubs_depletion":27.3,"shrubs_ETc":3.03,"shrubs_Kc":0.853,"shrubs_irrigation":0,"shrubs_drainage":0.0,"shrubs_interception":0.0,"shrubs_Kcb":0.733,"shrubs_Ke":0.12,"shrubs_E":0.43,"shrubs_T":2.6,"shrubs_De":9.83,"shrubs_few":0.1},{"date":"2026-04-28","Tmax":20.1,"Tmin":7.3,"Tmean":13.5,"RHmean":52.1,"u2":0.0,"Rs":null,"precip":0.0,"ET0_om":null,"precip_prob":0,"era5_theta_lawn":null,"era5_theta_shrubs":null,"forecast":false,"partial_factor":1.0,"hasWU":true,"ET0":3.5514814814814826,"lawn_theta":0.1143,"lawn_depletion":77.9,"lawn_ETc":1.73,"lawn_Kc":0.487,"lawn_irrigation":0,"lawn_drainage":0.0,"lawn_interception":0.0,"lawn_Kcb":0.855,"lawn_Ke":0.06,"lawn_E":0.21,"lawn_T":1.52,"lawn_De":2.68,"lawn_few":0.05,"shrubs_theta":0.1639,"shrubs_depletion":32.8,"shrubs_ETc":3.04,"shrubs_Kc":0.855,"shrubs_irrigation":0,"shrubs_drainage":0.0,"shrubs_interception":0.0,"shrubs_Kcb":0.735,"shrubs_Ke":0.12,"shrubs_E":0.43,"shrubs_T":2.61,"shrubs_De":10.26,"shrubs_few":0.1},{"date":"2026-04-29","Tmax":20.3,"Tmin":7.6,"Tmean":14.0,"RHmean":37.8,"u2":0.0,"Rs":null,"precip":0.0,"ET0_om":null,"precip_prob":0,"era5_theta_lawn":null,"era5_theta_shrubs":null,"forecast":false,"partial_factor":1.0,"hasWU":true,"ET0":3.5514814814814826,"lawn_theta":0.1411,"lawn_depletion":53.5,"lawn_ETc":1.33,"lawn_Kc":0.376,"lawn_irrigation":6.7,"lawn_drainage":0.0,"lawn_interception":0.0,"lawn_Kcb":0.857,"lawn_Ke":0.06,"lawn_E":0.21,"lawn_T":1.12,"lawn_De":0.21,"lawn_few":0.05,"shrubs_theta":0.1859,"shrubs_depletion":12.9,"shrubs_ETc":3.04,"shrubs_Kc":0.857,"shrubs_irrigation":14,"shrubs_drainage":0.0,"shrubs_interception":0.0,"shrubs_Kcb":0.737,"shrubs_Ke":0.12,"shrubs_E":0.43,"shrubs_T":2.62,"shrubs_De":0.43,"shrubs_few":0.1},{"date":"2026-04-30","Tmax":21.5,"Tmin":7.9,"Tmean":15.0,"RHmean":34.1,"u2":0.0,"Rs":null,"precip":0.0,"ET0_om":null,"precip_prob":0,"era5_theta_lawn":null,"era5_theta_shrubs":null,"forecast":false,"partial_factor":1.0,"hasWU":true,"ET0":3.551481481481483,"lawn_theta":0.1668,"lawn_depletion":30.2,"lawn_ETc":2.57,"lawn_Kc":0.725,"lawn_irrigation":7.7,"lawn_drainage":0.0,"lawn_interception":0.0,"lawn_Kcb":0.858,"lawn_Ke":0.06,"lawn_E":0.21,"lawn_T":2.36,"lawn_De":0.21,"lawn_few":0.05,"shrubs_theta":0.1814,"shrubs_depletion":16.9,"shrubs_ETc":3.05,"shrubs_Kc":0.858,"shrubs_irrigation":0.8,"shrubs_drainage":0.0,"shrubs_interception":0.0,"shrubs_Kcb":0.738,"shrubs_Ke":0.12,"shrubs_E":0.43,"shrubs_T":2.62,"shrubs_De":0.43,"shrubs_few":0.1},{"date":"2026-05-01","Tmax":25.5,"Tmin":10.0,"Tmean":17.7,"RHmean":37.8,"u2":0.0,"Rs":null,"precip":0.0,"ET0_om":null,"precip_prob":0,"era5_theta_lawn":null,"era5_theta_shrubs":null,"forecast":false,"partial_factor":1.0,"hasWU":true,"ET0":3.551481481481482,"lawn_theta":0.1504,"lawn_depletion":45.1,"lawn_ETc":3.27,"lawn_Kc":0.92,"lawn_irrigation":0,"lawn_drainage":0.0,"lawn_interception":0.0,"lawn_Kcb":0.86,"lawn_Ke":0.06,"lawn_E":0.21,"lawn_T":3.05,"lawn_De":0.43,"lawn_few":0.05,"shrubs_theta":0.1752,"shrubs_depletion":22.5,"shrubs_ETc":3.05,"shrubs_Kc":0.86,"shrubs_irrigation":0,"shrubs_drainage":0.0,"shrubs_interception":0.0,"shrubs_Kcb":0.74,"shrubs_Ke":0.12,"shrubs_E":0.43,"shrubs_T":2.63,"shrubs_De":0.85,"shrubs_few":0.1},{"date":"2026-05-02","Tmax":26.1,"Tmin":9.8,"Tmean":17.5,"RHmean":57.8,"u2":0.0,"Rs":null,"precip":2.11,"ET0_om":null,"precip_prob":43,"era5_theta_lawn":null,"era5_theta_shrubs":null,"forecast":false,"partial_factor":1.0,"hasWU":true,"ET0":3.5514814814814826,"lawn_theta":0.1415,"lawn_depletion":53.2,"lawn_ETc":3.01,"lawn_Kc":0.848,"lawn_irrigation":0,"lawn_drainage":0.0,"lawn_interception":0.88,"lawn_Kcb":0.861,"lawn_Ke":0.06,"lawn_E":0.21,"lawn_T":2.8,"lawn_De":0.21,"lawn_few":0.05,"shrubs_theta":0.1711,"shrubs_depletion":26.3,"shrubs_ETc":3.06,"shrubs_Kc":0.863,"shrubs_irrigation":0,"shrubs_drainage":0.0,"shrubs_interception":1.13,"shrubs_Kcb":0.743,"shrubs_Ke":0.12,"shrubs_E":0.43,"shrubs_T":2.64,"shrubs_De":0.43,"shrubs_few":0.1},{"date":"2026-05-03","Tmax":19.0,"Tmin":12.8,"Tmean":15.2,"RHmean":89.2,"u2":0.0,"Rs":null,"precip":10.9,"ET0_om":null,"precip_prob":100,"era5_theta_lawn":null,"era5_theta_shrubs":null,"forecast":false,"partial_factor":1.0,"hasWU":true,"ET0":3.551481481481482,"lawn_theta":0.178,"lawn_depletion":20.0,"lawn_ETc":2.61,"lawn_Kc":0.734,"lawn_irrigation":0,"lawn_drainage":0.0,"lawn_interception":1.0,"lawn_Kcb":0.863,"lawn_Ke":0.06,"lawn_E":0.21,"lawn_T":2.39,"lawn_De":0.21,"lawn_few":0.05,"shrubs_theta":0.1837,"shrubs_depletion":14.8,"shrubs_ETc":3.08,"shrubs_Kc":0.866,"shrubs_irrigation":0,"shrubs_drainage":0.0,"shrubs_interception":1.5,"shrubs_Kcb":0.746,"shrubs_Ke":0.12,"shrubs_E":0.43,"shrubs_T":2.65,"shrubs_De":0.43,"shrubs_few":0.1},{"date":"2026-05-04","Tmax":20.9,"Tmin":11.6,"Tmean":14.9,"RHmean":84.4,"u2":0.0,"Rs":null,"precip":0.0,"ET0_om":null,"precip_prob":98,"era5_theta_lawn":null,"era5_theta_shrubs":null,"forecast":false,"partial_factor":1.0,"hasWU":true,"ET0":3.5514814814814826,"lawn_theta":0.1616,"lawn_depletion":34.9,"lawn_ETc":3.28,"lawn_Kc":0.924,"lawn_irrigation":0,"lawn_drainage":0.0,"lawn_interception":0.0,"lawn_Kcb":0.864,"lawn_Ke":0.06,"lawn_E":0.21,"lawn_T":3.07,"lawn_De":0.43,"lawn_few":0.05,"shrubs_theta":0.1776,"shrubs_depletion":20.4,"shrubs_ETc":3.09,"shrubs_Kc":0.869,"shrubs_irrigation":0,"shrubs_drainage":0.0,"shrubs_interception":0.0,"shrubs_Kcb":0.749,"shrubs_Ke":0.12,"shrubs_E":0.43,"shrubs_T":2.66,"shrubs_De":0.85,"shrubs_few":0.1},{"date":"2026-05-05","Tmax":17.3,"Tmin":9.4,"Tmean":12.0,"RHmean":76.2,"u2":0.0,"Rs":null,"precip":0.0,"ET0_om":null,"precip_prob":6,"era5_theta_lawn":null,"era5_theta_shrubs":null,"forecast":false,"partial_factor":1.0,"hasWU":true,"ET0":3.5514814814814817,"lawn_theta":0.1452,"lawn_depletion":49.9,"lawn_ETc":3.29,"lawn_Kc":0.925,"lawn_irrigation":0,"lawn_drainage":0.0,"lawn_interception":0.0,"lawn_Kcb":0.865,"lawn_Ke":0.06,"lawn_E":0.21,"lawn_T":3.07,"lawn_De":0.64,"lawn_few":0.05,"shrubs_theta":0.1714,"shrubs_depletion":26.0,"shrubs_ETc":3.1,"shrubs_Kc":0.872,"shrubs_irrigation":0,"shrubs_drainage":0.0,"shrubs_interception":0.0,"shrubs_Kcb":0.752,"shrubs_Ke":0.12,"shrubs_E":0.43,"shrubs_T":2.67,"shrubs_De":1.28,"shrubs_few":0.1},{"date":"2026-05-06","Tmax":14.9,"Tmin":9.7,"Tmean":12.0,"RHmean":65.3,"u2":0.0,"Rs":null,"precip":0.0,"ET0_om":null,"precip_prob":35,"era5_theta_lawn":null,"era5_theta_shrubs":null,"forecast":false,"partial_factor":1.0,"hasWU":true,"ET0":3.5514814814814812,"lawn_theta":0.1312,"lawn_depletion":62.5,"lawn_ETc":2.78,"lawn_Kc":0.784,"lawn_irrigation":0,"lawn_drainage":0.0,"lawn_interception":0.0,"lawn_Kcb":0.866,"lawn_Ke":0.06,"lawn_E":0.21,"lawn_T":2.57,"lawn_De":0.85,"lawn_few":0.05,"shrubs_theta":0.1971,"shrubs_depletion":2.6,"shrubs_ETc":3.11,"shrubs_Kc":0.875,"shrubs_irrigation":16,"shrubs_drainage":0.0,"shrubs_interception":0.0,"shrubs_Kcb":0.755,"shrubs_Ke":0.12,"shrubs_E":0.43,"shrubs_T":2.68,"shrubs_De":0.43,"shrubs_few":0.1},{"date":"2026-05-07","Tmax":18.7,"Tmin":6.5,"Tmean":12.7,"RHmean":65.0,"u2":0.0,"Rs":null,"precip":0.0,"ET0_om":null,"precip_prob":2,"era5_theta_lawn":null,"era5_theta_shrubs":null,"forecast":false,"partial_factor":1.0,"hasWU":true,"ET0":3.5514814814814812,"lawn_theta":0.1205,"lawn_depletion":72.2,"lawn_ETc":2.14,"lawn_Kc":0.602,"lawn_irrigation":0,"lawn_drainage":0.0,"lawn_interception":0.0,"lawn_Kcb":0.868,"lawn_Ke":0.06,"lawn_E":0.21,"lawn_T":1.93,"lawn_De":1.07,"lawn_few":0.05,"shrubs_theta":0.1909,"shrubs_depletion":8.3,"shrubs_ETc":3.11,"shrubs_Kc":0.877,"shrubs_irrigation":0,"shrubs_drainage":0.0,"shrubs_interception":0.0,"shrubs_Kcb":0.757,"shrubs_Ke":0.12,"shrubs_E":0.43,"shrubs_T":2.69,"shrubs_De":0.85,"shrubs_few":0.1},{"date":"2026-05-08","Tmax":19.2,"Tmin":8.7,"Tmean":13.2,"RHmean":67.7,"u2":0.0,"Rs":18.35,"precip":0.0,"ET0_om":3.06,"precip_prob":6,"era5_theta_lawn":null,"era5_theta_shrubs":null,"forecast":false,"partial_factor":1.0,"hasWU":true,"ET0":2.63,"lawn_theta":0.173,"lawn_depletion":24.6,"lawn_ETc":1.22,"lawn_Kc":0.462,"lawn_irrigation":11.7,"lawn_drainage":0.0,"lawn_interception":0.0,"lawn_Kcb":0.869,"lawn_Ke":0.06,"lawn_E":0.16,"lawn_T":1.06,"lawn_De":0.16,"lawn_few":0.05,"shrubs_theta":0.1887,"shrubs_depletion":10.3,"shrubs_ETc":2.31,"shrubs_Kc":0.88,"shrubs_irrigation":1.2,"shrubs_drainage":0.0,"shrubs_interception":0.0,"shrubs_Kcb":0.76,"shrubs_Ke":0.12,"shrubs_E":0.32,"shrubs_T":2.0,"shrubs_De":0.32,"shrubs_few":0.1},{"date":"2026-05-09","Tmax":21.7,"Tmin":6.4,"Tmean":13.9,"RHmean":64.4,"u2":0.0,"Rs":23.3,"precip":0.0,"ET0_om":4.0,"precip_prob":0,"era5_theta_lawn":null,"era5_theta_shrubs":null,"forecast":false,"partial_factor":1.0,"hasWU":true,"ET0":3.2,"lawn_theta":0.1581,"lawn_depletion":38.1,"lawn_ETc":2.98,"lawn_Kc":0.93,"lawn_irrigation":0,"lawn_drainage":0.0,"lawn_interception":0.0,"lawn_Kcb":0.87,"lawn_Ke":0.06,"lawn_E":0.19,"lawn_T":2.78,"lawn_De":0.35,"lawn_few":0.05,"shrubs_theta":0.183,"shrubs_depletion":15.4,"shrubs_ETc":2.83,"shrubs_Kc":0.883,"shrubs_irrigation":0,"shrubs_drainage":0.0,"shrubs_interception":0.0,"shrubs_Kcb":0.763,"shrubs_Ke":0.12,"shrubs_E":0.38,"shrubs_T":2.44,"shrubs_De":0.7,"shrubs_few":0.1},{"date":"2026-05-10","Tmax":18.3,"Tmin":8.4,"Tmean":13.1,"RHmean":69.3,"u2":0.0,"Rs":22.23,"precip":0.0,"ET0_om":3.75,"precip_prob":2,"era5_theta_lawn":null,"era5_theta_shrubs":null,"forecast":false,"partial_factor":1.0,"hasWU":true,"ET0":3.04,"lawn_theta":0.1439,"lawn_depletion":51.0,"lawn_ETc":2.83,"lawn_Kc":0.932,"lawn_irrigation":0,"lawn_drainage":0.0,"lawn_interception":0.0,"lawn_Kcb":0.872,"lawn_Ke":0.06,"lawn_E":0.18,"lawn_T":2.65,"lawn_De":0.53,"lawn_few":0.05,"shrubs_theta":0.1776,"shrubs_depletion":20.3,"shrubs_ETc":2.69,"shrubs_Kc":0.886,"shrubs_irrigation":0,"shrubs_drainage":0.0,"shrubs_interception":0.0,"shrubs_Kcb":0.766,"shrubs_Ke":0.12,"shrubs_E":0.36,"shrubs_T":2.33,"shrubs_De":1.06,"shrubs_few":0.1},{"date":"2026-05-11","Tmax":14.5,"Tmin":5.2,"Tmean":9.0,"RHmean":68.2,"u2":0.0,"Rs":17.37,"precip":2.01,"ET0_om":2.71,"precip_prob":98,"era5_theta_lawn":null,"era5_theta_shrubs":null,"forecast":false,"partial_factor":1.0,"hasWU":true,"ET0":2.27,"lawn_theta":0.1409,"lawn_depletion":53.8,"lawn_ETc":1.76,"lawn_Kc":0.773,"lawn_irrigation":0,"lawn_drainage":0.0,"lawn_interception":0.87,"lawn_Kcb":0.873,"lawn_Ke":0.06,"lawn_E":0.14,"lawn_T":1.62,"lawn_De":0.14,"lawn_few":0.05,"shrubs_theta":0.1754,"shrubs_depletion":22.3,"shrubs_ETc":2.02,"shrubs_Kc":0.889,"shrubs_irrigation":0,"shrubs_drainage":0.0,"shrubs_interception":1.11,"shrubs_Kcb":0.769,"shrubs_Ke":0.12,"shrubs_E":0.27,"shrubs_T":1.75,"shrubs_De":0.43,"shrubs_few":0.1},{"date":"2026-05-12","Tmax":13.6,"Tmin":5.1,"Tmean":9.4,"RHmean":69.6,"u2":0.0,"Rs":12.69,"precip":0.99,"ET0_om":2.4,"precip_prob":96,"era5_theta_lawn":null,"era5_theta_shrubs":null,"forecast":false,"partial_factor":1.0,"hasWU":true,"ET0":1.78,"lawn_theta":0.1361,"lawn_depletion":58.1,"lawn_ETc":1.31,"lawn_Kc":0.734,"lawn_irrigation":0,"lawn_drainage":0.0,"lawn_interception":0.63,"lawn_Kcb":0.874,"lawn_Ke":0.06,"lawn_E":0.11,"lawn_T":1.2,"lawn_De":0.11,"lawn_few":0.05,"shrubs_theta":0.1728,"shrubs_depletion":24.8,"shrubs_ETc":1.59,"shrubs_Kc":0.892,"shrubs_irrigation":0,"shrubs_drainage":0.0,"shrubs_interception":0.72,"shrubs_Kcb":0.772,"shrubs_Ke":0.12,"shrubs_E":0.21,"shrubs_T":1.37,"shrubs_De":0.38,"shrubs_few":0.1},{"date":"2026-05-13","Tmax":15.9,"Tmin":6.2,"Tmean":10.2,"RHmean":76.2,"u2":0.0,"Rs":16.91,"precip":2.11,"ET0_om":2.2,"precip_prob":100,"era5_theta_lawn":null,"era5_theta_shrubs":null,"forecast":false,"partial_factor":1.0,"hasWU":true,"ET0":2.34,"lawn_theta":0.1344,"lawn_depletion":59.6,"lawn_ETc":1.57,"lawn_Kc":0.672,"lawn_irrigation":0,"lawn_drainage":0.0,"lawn_interception":0.88,"lawn_Kcb":0.875,"lawn_Ke":0.06,"lawn_E":0.14,"lawn_T":1.43,"lawn_De":0.14,"lawn_few":0.05,"shrubs_theta":0.1705,"shrubs_depletion":26.8,"shrubs_ETc":2.09,"shrubs_Kc":0.895,"shrubs_irrigation":0,"shrubs_drainage":0.0,"shrubs_interception":1.13,"shrubs_Kcb":0.775,"shrubs_Ke":0.12,"shrubs_E":0.28,"shrubs_T":1.81,"shrubs_De":0.28,"shrubs_few":0.1},{"date":"2026-05-14","Tmax":15.2,"Tmin":4.5,"Tmean":9.3,"RHmean":74.2,"u2":0.0,"Rs":19.31,"precip":2.01,"ET0_om":2.44,"precip_prob":98,"era5_theta_lawn":null,"era5_theta_shrubs":null,"forecast":false,"partial_factor":1.0,"hasWU":true,"ET0":2.51,"lawn_theta":0.132,"lawn_depletion":61.8,"lawn_ETc":1.63,"lawn_Kc":0.651,"lawn_irrigation":0,"lawn_drainage":0.0,"lawn_interception":0.87,"lawn_Kcb":0.877,"lawn_Ke":0.06,"lawn_E":0.15,"lawn_T":1.48,"lawn_De":0.15,"lawn_few":0.05,"shrubs_theta":0.1678,"shrubs_depletion":29.2,"shrubs_ETc":2.25,"shrubs_Kc":0.898,"shrubs_irrigation":0,"shrubs_drainage":0.0,"shrubs_interception":1.11,"shrubs_Kcb":0.778,"shrubs_Ke":0.12,"shrubs_E":0.3,"shrubs_T":1.95,"shrubs_De":0.3,"shrubs_few":0.1},{"date":"2026-05-15","Tmax":15.0,"Tmin":3.1,"Tmean":8.2,"RHmean":77.6,"u2":0.0,"Rs":18.09,"precip":1.3,"ET0_om":2.31,"precip_prob":87,"era5_theta_lawn":null,"era5_theta_shrubs":null,"forecast":false,"partial_factor":1.0,"hasWU":true,"ET0":2.35,"lawn_theta":0.1276,"lawn_depletion":65.8,"lawn_ETc":1.45,"lawn_Kc":0.619,"lawn_irrigation":0,"lawn_drainage":0.0,"lawn_interception":0.73,"lawn_Kcb":0.878,"lawn_Ke":0.06,"lawn_E":0.14,"lawn_T":1.31,"lawn_De":0.14,"lawn_few":0.05,"shrubs_theta":0.1645,"shrubs_depletion":32.3,"shrubs_ETc":2.12,"shrubs_Kc":0.901,"shrubs_irrigation":0,"shrubs_drainage":0.0,"shrubs_interception":0.87,"shrubs_Kcb":0.781,"shrubs_Ke":0.12,"shrubs_E":0.28,"shrubs_T":1.84,"shrubs_De":0.28,"shrubs_few":0.1},{"date":"2026-05-16","Tmax":15.0,"Tmin":3.7,"Tmean":9.1,"RHmean":72.5,"u2":0.0,"Rs":22.86,"precip":0.2,"ET0_om":2.99,"precip_prob":73,"era5_theta_lawn":null,"era5_theta_shrubs":null,"forecast":false,"partial_factor":1.0,"hasWU":true,"ET0":2.85,"lawn_theta":0.1197,"lawn_depletion":73.0,"lawn_ETc":1.6,"lawn_Kc":0.561,"lawn_irrigation":0,"lawn_drainage":0.0,"lawn_interception":0.18,"lawn_Kcb":0.879,"lawn_Ke":0.06,"lawn_E":0.17,"lawn_T":1.43,"lawn_De":0.29,"lawn_few":0.05,"shrubs_theta":0.1593,"shrubs_depletion":37.0,"shrubs_ETc":2.58,"shrubs_Kc":0.904,"shrubs_irrigation":0,"shrubs_drainage":0.0,"shrubs_interception":0.19,"shrubs_Kcb":0.784,"shrubs_Ke":0.12,"shrubs_E":0.34,"shrubs_T":2.23,"shrubs_De":0.61,"shrubs_few":0.1},{"date":"2026-05-17","Tmax":17.8,"Tmin":7.9,"Tmean":11.2,"RHmean":83.0,"u2":0.0,"Rs":15.13,"precip":7.59,"ET0_om":2.2,"precip_prob":100,"era5_theta_lawn":null,"era5_theta_shrubs":null,"forecast":false,"partial_factor":1.0,"hasWU":true,"ET0":2.3,"lawn_theta":0.1474,"lawn_depletion":47.8,"lawn_ETc":1.05,"lawn_Kc":0.456,"lawn_irrigation":0,"lawn_drainage":0.0,"lawn_interception":1.0,"lawn_Kcb":0.881,"lawn_Ke":0.06,"lawn_E":0.14,"lawn_T":0.91,"lawn_De":0.14,"lawn_few":0.05,"shrubs_theta":0.1964,"shrubs_depletion":3.3,"shrubs_ETc":2.08,"shrubs_Kc":0.906,"shrubs_irrigation":14.5,"shrubs_drainage":0.0,"shrubs_interception":1.49,"shrubs_Kcb":0.786,"shrubs_Ke":0.12,"shrubs_E":0.28,"shrubs_T":1.81,"shrubs_De":0.28,"shrubs_few":0.1},{"date":"2026-05-18","Tmax":18.5,"Tmin":7.9,"Tmean":12.4,"RHmean":83.6,"u2":0.0,"Rs":19.18,"precip":8.89,"ET0_om":2.6,"precip_prob":100,"era5_theta_lawn":null,"era5_theta_shrubs":null,"forecast":false,"partial_factor":1.0,"hasWU":true,"ET0":2.81,"lawn_theta":0.1752,"lawn_depletion":22.5,"lawn_ETc":2.32,"lawn_Kc":0.827,"lawn_irrigation":0,"lawn_drainage":0.0,"lawn_interception":1.0,"lawn_Kcb":0.882,"lawn_Ke":0.06,"lawn_E":0.17,"lawn_T":2.16,"lawn_De":0.17,"lawn_few":0.05,"shrubs_theta":0.2,"shrubs_depletion":0.0,"shrubs_ETc":2.55,"shrubs_Kc":0.909,"shrubs_irrigation":0,"shrubs_drainage":3.02,"shrubs_interception":1.5,"shrubs_Kcb":0.789,"shrubs_Ke":0.12,"shrubs_E":0.34,"shrubs_T":2.22,"shrubs_De":0.34,"shrubs_few":0.1},{"date":"2026-05-19","Tmax":18.5,"Tmin":7.1,"Tmean":12.2,"RHmean":83.7,"u2":0.0,"Rs":11.96,"precip":4.6,"ET0_om":1.81,"precip_prob":100,"era5_theta_lawn":null,"era5_theta_shrubs":null,"forecast":false,"partial_factor":1.0,"hasWU":true,"ET0":1.93,"lawn_theta":0.1842,"lawn_depletion":14.4,"lawn_ETc":1.82,"lawn_Kc":0.943,"lawn_irrigation":0,"lawn_drainage":0.0,"lawn_interception":0.99,"lawn_Kcb":0.883,"lawn_Ke":0.06,"lawn_E":0.12,"lawn_T":1.7,"lawn_De":0.12,"lawn_few":0.05,"shrubs_theta":0.2,"shrubs_depletion":0.0,"shrubs_ETc":1.76,"shrubs_Kc":0.912,"shrubs_irrigation":0,"shrubs_drainage":1.41,"shrubs_interception":1.43,"shrubs_Kcb":0.792,"shrubs_Ke":0.12,"shrubs_E":0.23,"shrubs_T":1.53,"shrubs_De":0.23,"shrubs_few":0.1},{"date":"2026-05-20","Tmax":20.2,"Tmin":12.3,"Tmean":14.9,"RHmean":81.6,"u2":0.0,"Rs":19.68,"precip":3.81,"ET0_om":2.84,"precip_prob":98,"era5_theta_lawn":null,"era5_theta_shrubs":null,"forecast":false,"partial_factor":1.0,"hasWU":true,"ET0":3.11,"lawn_theta":0.1836,"lawn_depletion":14.9,"lawn_ETc":2.94,"lawn_Kc":0.945,"lawn_irrigation":0,"lawn_drainage":0.0,"lawn_interception":0.98,"lawn_Kcb":0.885,"lawn_Ke":0.06,"lawn_E":0.19,"lawn_T":2.75,"lawn_De":0.19,"lawn_few":0.05,"shrubs_theta":0.1992,"shrubs_depletion":0.8,"shrubs_ETc":2.85,"shrubs_Kc":0.915,"shrubs_irrigation":0,"shrubs_drainage":0.0,"shrubs_interception":1.38,"shrubs_Kcb":0.795,"shrubs_Ke":0.12,"shrubs_E":0.37,"shrubs_T":2.47,"shrubs_De":0.37,"shrubs_few":0.1},{"date":"2026-05-21","Tmax":23.5,"Tmin":12.0,"Tmean":17.0,"RHmean":74.0,"u2":0.0,"Rs":23.94,"precip":0.0,"ET0_om":3.59,"precip_prob":6,"era5_theta_lawn":0.7168,"era5_theta_shrubs":0.7236,"forecast":false,"partial_factor":1.0,"hasWU":true,"ET0":3.78,"lawn_theta":0.1658,"lawn_depletion":31.1,"lawn_ETc":3.58,"lawn_Kc":0.946,"lawn_irrigation":0,"lawn_drainage":0.0,"lawn_interception":0.0,"lawn_Kcb":0.886,"lawn_Ke":0.06,"lawn_E":0.23,"lawn_T":3.35,"lawn_De":0.41,"lawn_few":0.05,"shrubs_theta":0.1922,"shrubs_depletion":7.1,"shrubs_ETc":3.47,"shrubs_Kc":0.918,"shrubs_irrigation":0,"shrubs_drainage":0.0,"shrubs_interception":0.0,"shrubs_Kcb":0.798,"shrubs_Ke":0.12,"shrubs_E":0.45,"shrubs_T":3.02,"shrubs_De":0.83,"shrubs_few":0.1},{"date":"2026-05-22","Tmax":28.3,"Tmin":11.1,"Tmean":19.6,"RHmean":66.9,"u2":0.0,"Rs":27.59,"precip":0.0,"ET0_om":5.43,"precip_prob":0,"era5_theta_lawn":0.7108,"era5_theta_shrubs":0.7213,"forecast":false,"partial_factor":1.0,"hasWU":true,"ET0":4.46,"lawn_theta":0.1446,"lawn_depletion":50.3,"lawn_ETc":4.22,"lawn_Kc":0.947,"lawn_irrigation":0,"lawn_drainage":0.0,"lawn_interception":0.0,"lawn_Kcb":0.887,"lawn_Ke":0.06,"lawn_E":0.27,"lawn_T":3.96,"lawn_De":0.68,"lawn_few":0.05,"shrubs_theta":0.184,"shrubs_depletion":14.5,"shrubs_ETc":4.11,"shrubs_Kc":0.921,"shrubs_irrigation":0,"shrubs_drainage":0.0,"shrubs_interception":0.0,"shrubs_Kcb":0.801,"shrubs_Ke":0.12,"shrubs_E":0.54,"shrubs_T":3.57,"shrubs_De":1.36,"shrubs_few":0.1},{"date":"2026-05-23","Tmax":32.6,"Tmin":13.6,"Tmean":22.6,"RHmean":64.4,"u2":0.0,"Rs":27.09,"precip":0.0,"ET0_om":6.06,"precip_prob":0,"era5_theta_lawn":0.7026,"era5_theta_shrubs":0.7178,"forecast":false,"partial_factor":1.0,"hasWU":true,"ET0":4.75,"lawn_theta":0.1343,"lawn_depletion":59.8,"lawn_ETc":3.78,"lawn_Kc":0.795,"lawn_irrigation":1.7,"lawn_drainage":0.0,"lawn_interception":0.0,"lawn_Kcb":0.888,"lawn_Ke":0.06,"lawn_E":0.29,"lawn_T":3.49,"lawn_De":0.29,"lawn_few":0.05,"shrubs_theta":0.1778,"shrubs_depletion":20.2,"shrubs_ETc":4.39,"shrubs_Kc":0.924,"shrubs_irrigation":1.3,"shrubs_drainage":0.0,"shrubs_interception":0.0,"shrubs_Kcb":0.804,"shrubs_Ke":0.12,"shrubs_E":0.57,"shrubs_T":3.82,"shrubs_De":0.63,"shrubs_few":0.1},{"date":"2026-05-24","Tmax":29.9,"Tmin":14.4,"Tmean":21.1,"RHmean":63.7,"u2":0.0,"Rs":27.63,"precip":0.0,"ET0_om":5.57,"precip_prob":0,"era5_theta_lawn":0.6961,"era5_theta_shrubs":0.7147,"forecast":false,"partial_factor":1.0,"hasWU":true,"ET0":4.68,"lawn_theta":0.1189,"lawn_depletion":73.7,"lawn_ETc":3.07,"lawn_Kc":0.657,"lawn_irrigation":0,"lawn_drainage":0.0,"lawn_interception":0.0,"lawn_Kcb":0.89,"lawn_Ke":0.06,"lawn_E":0.28,"lawn_T":2.79,"lawn_De":0.57,"lawn_few":0.05,"shrubs_theta":0.1692,"shrubs_depletion":28.0,"shrubs_ETc":4.34,"shrubs_Kc":0.927,"shrubs_irrigation":0,"shrubs_drainage":0.0,"shrubs_interception":0.0,"shrubs_Kcb":0.807,"shrubs_Ke":0.12,"shrubs_E":0.56,"shrubs_T":3.78,"shrubs_De":1.19,"shrubs_few":0.1},{"date":"2026-05-25","Tmax":31.7,"Tmin":11.8,"Tmean":21.8,"RHmean":56.9,"u2":0.0,"Rs":28.38,"precip":0.0,"ET0_om":6.12,"precip_prob":0,"era5_theta_lawn":0.6913,"era5_theta_shrubs":0.7123,"forecast":false,"partial_factor":1.0,"hasWU":true,"ET0":4.7,"lawn_theta":0.1833,"lawn_depletion":15.2,"lawn_ETc":2.12,"lawn_Kc":0.45,"lawn_irrigation":15,"lawn_drainage":0.0,"lawn_interception":0.0,"lawn_Kcb":0.891,"lawn_Ke":0.06,"lawn_E":0.28,"lawn_T":1.83,"lawn_De":0.28,"lawn_few":0.05,"shrubs_theta":0.1604,"shrubs_depletion":36.0,"shrubs_ETc":4.37,"shrubs_Kc":0.93,"shrubs_irrigation":0,"shrubs_drainage":0.0,"shrubs_interception":0.0,"shrubs_Kcb":0.81,"shrubs_Ke":0.12,"shrubs_E":0.56,"shrubs_T":3.81,"shrubs_De":1.76,"shrubs_few":0.1},{"date":"2026-05-26","Tmax":35.0,"Tmin":13.7,"Tmean":23.9,"RHmean":55.8,"u2":0.0,"Rs":27.58,"precip":0.0,"ET0_om":6.25,"precip_prob":0,"era5_theta_lawn":0.6859,"era5_theta_shrubs":0.7093,"forecast":false,"partial_factor":1.0,"hasWU":true,"ET0":4.87,"lawn_theta":0.1601,"lawn_depletion":36.2,"lawn_ETc":4.64,"lawn_Kc":0.952,"lawn_irrigation":0,"lawn_drainage":0.0,"lawn_interception":0.0,"lawn_Kcb":0.892,"lawn_Ke":0.06,"lawn_E":0.29,"lawn_T":4.34,"lawn_De":0.57,"lawn_few":0.05,"shrubs_theta":0.1513,"shrubs_depletion":44.2,"shrubs_ETc":4.54,"shrubs_Kc":0.933,"shrubs_irrigation":0,"shrubs_drainage":0.0,"shrubs_interception":0.0,"shrubs_Kcb":0.813,"shrubs_Ke":0.12,"shrubs_E":0.58,"shrubs_T":3.96,"shrubs_De":2.34,"shrubs_few":0.1},{"date":"2026-05-27","Tmax":25.4,"Tmin":15.5,"Tmean":19.7,"RHmean":60.6,"u2":0.0,"Rs":23.92,"precip":0.0,"ET0_om":5.2,"precip_prob":47,"era5_theta_lawn":0.6797,"era5_theta_shrubs":0.7061,"forecast":false,"partial_factor":1.0,"hasWU":true,"ET0":3.93,"lawn_theta":0.1414,"lawn_depletion":53.3,"lawn_ETc":3.75,"lawn_Kc":0.954,"lawn_irrigation":0,"lawn_drainage":0.0,"lawn_interception":0.0,"lawn_Kcb":0.894,"lawn_Ke":0.06,"lawn_E":0.24,"lawn_T":3.51,"lawn_De":0.81,"lawn_few":0.05,"shrubs_theta":0.2,"shrubs_depletion":0.0,"shrubs_ETc":3.67,"shrubs_Kc":0.935,"shrubs_irrigation":50,"shrubs_drainage":21.99,"shrubs_interception":0.0,"shrubs_Kcb":0.815,"shrubs_Ke":0.12,"shrubs_E":0.47,"shrubs_T":3.2,"shrubs_De":0.47,"shrubs_few":0.1},{"date":"2026-05-28","Tmax":26.1,"Tmin":12.4,"Tmean":19.6,"RHmean":40,"u2":2.0776418754665116,"Rs":27.89,"precip":0.0,"ET0_om":5.97,"precip_prob":0,"era5_theta_lawn":0.6759,"era5_theta_shrubs":0.7037,"forecast":false,"partial_factor":0.9535243996901627,"hasWU":true,"ET0":5.52,"lawn_theta":0.179,"lawn_depletion":19.1,"lawn_ETc":4.18,"lawn_Kc":0.757,"lawn_irrigation":11.7,"lawn_drainage":0.0,"lawn_interception":0.0,"lawn_Kcb":0.895,"lawn_Ke":0.06,"lawn_E":0.33,"lawn_T":3.85,"lawn_De":0.33,"lawn_few":0.05,"shrubs_theta":0.193,"shrubs_depletion":6.3,"shrubs_ETc":5.18,"shrubs_Kc":0.938,"shrubs_irrigation":1.7,"shrubs_drainage":0.0,"shrubs_interception":0.0,"shrubs_Kcb":0.818,"shrubs_Ke":0.12,"shrubs_E":0.66,"shrubs_T":4.52,"shrubs_De":0.66,"shrubs_few":0.1},{"date":"2026-05-29","Tmax":32.0,"Tmin":19.2,"Tmean":24.0,"RHmean":44,"u2":2.6386051818424696,"Rs":19.81,"precip":0.3,"ET0_om":5.84,"precip_prob":42,"era5_theta_lawn":0.6705,"era5_theta_shrubs":0.701,"forecast":true,"partial_factor":1.0,"ET0":6.15,"lawn_theta":0.1498,"lawn_depletion":45.6,"lawn_ETc":5.88,"lawn_Kc":0.956,"lawn_irrigation":0,"lawn_drainage":0.0,"lawn_interception":0.26,"lawn_Kcb":0.896,"lawn_Ke":0.06,"lawn_E":0.37,"lawn_T":5.51,"lawn_De":0.66,"lawn_few":0.05,"shrubs_theta":0.1815,"shrubs_depletion":16.8,"shrubs_ETc":5.79,"shrubs_Kc":0.941,"shrubs_irrigation":0,"shrubs_drainage":0.0,"shrubs_interception":0.27,"shrubs_Kcb":0.821,"shrubs_Ke":0.12,"shrubs_E":0.74,"shrubs_T":5.05,"shrubs_De":1.37,"shrubs_few":0.1},{"date":"2026-05-30","Tmax":27.5,"Tmin":17.6,"Tmean":22.2,"RHmean":51,"u2":2.1191947129758413,"Rs":25.49,"precip":0.1,"ET0_om":5.81,"precip_prob":32,"era5_theta_lawn":0.6683,"era5_theta_shrubs":0.6992,"forecast":true,"partial_factor":1.0,"ET0":5.65,"lawn_theta":0.1252,"lawn_depletion":68.0,"lawn_ETc":4.93,"lawn_Kc":0.873,"lawn_irrigation":0,"lawn_drainage":0.0,"lawn_interception":0.1,"lawn_Kcb":0.897,"lawn_Ke":0.06,"lawn_E":0.34,"lawn_T":4.59,"lawn_De":0.99,"lawn_few":0.05,"shrubs_theta":0.1709,"shrubs_depletion":26.5,"shrubs_ETc":5.33,"shrubs_Kc":0.944,"shrubs_irrigation":0,"shrubs_drainage":0.0,"shrubs_interception":0.1,"shrubs_Kcb":0.824,"shrubs_Ke":0.12,"shrubs_E":0.68,"shrubs_T":4.66,"shrubs_De":2.05,"shrubs_few":0.1},{"date":"2026-05-31","Tmax":23.8,"Tmin":15.4,"Tmean":19.1,"RHmean":64,"u2":2.0568654567118463,"Rs":19.07,"precip":0.8,"ET0_om":4.03,"precip_prob":33,"era5_theta_lawn":0.6707,"era5_theta_shrubs":0.6989,"forecast":true,"partial_factor":1.0,"ET0":4.04,"lawn_theta":0.1155,"lawn_depletion":76.8,"lawn_ETc":2.18,"lawn_Kc":0.539,"lawn_irrigation":0,"lawn_drainage":0.0,"lawn_interception":0.55,"lawn_Kcb":0.899,"lawn_Ke":0.06,"lawn_E":0.24,"lawn_T":1.94,"lawn_De":0.99,"lawn_few":0.05,"shrubs_theta":0.1636,"shrubs_depletion":33.1,"shrubs_ETc":3.83,"shrubs_Kc":0.947,"shrubs_irrigation":0,"shrubs_drainage":0.0,"shrubs_interception":0.62,"shrubs_Kcb":0.827,"shrubs_Ke":0.12,"shrubs_E":0.48,"shrubs_T":3.34,"shrubs_De":2.35,"shrubs_few":0.1},{"date":"2026-06-01","Tmax":22.0,"Tmin":14.2,"Tmean":18.6,"RHmean":70,"u2":2.223076806749167,"Rs":25.03,"precip":0.3,"ET0_om":4.53,"precip_prob":29,"era5_theta_lawn":0.6679,"era5_theta_shrubs":0.6972,"forecast":true,"partial_factor":1.0,"ET0":4.35,"lawn_theta":0.1069,"lawn_depletion":84.7,"lawn_ETc":1.78,"lawn_Kc":0.408,"lawn_irrigation":0,"lawn_drainage":0.0,"lawn_interception":0.26,"lawn_Kcb":0.9,"lawn_Ke":0.06,"lawn_E":0.26,"lawn_T":1.51,"lawn_De":1.21,"lawn_few":0.05,"shrubs_theta":0.1554,"shrubs_depletion":40.6,"shrubs_ETc":4.13,"shrubs_Kc":0.95,"shrubs_irrigation":0,"shrubs_drainage":0.0,"shrubs_interception":0.27,"shrubs_Kcb":0.83,"shrubs_Ke":0.12,"shrubs_E":0.52,"shrubs_T":3.61,"shrubs_De":2.85,"shrubs_few":0.1},{"date":"2026-06-02","Tmax":18.4,"Tmin":15.2,"Tmean":17.0,"RHmean":82,"u2":2.887922206898451,"Rs":11.77,"precip":19.2,"ET0_om":2.14,"precip_prob":86,"era5_theta_lawn":0.6944,"era5_theta_shrubs":0.7049,"forecast":true,"partial_factor":1.0,"ET0":2.39,"lawn_theta":0.1944,"lawn_depletion":5.1,"lawn_ETc":0.69,"lawn_Kc":0.29,"lawn_irrigation":0,"lawn_drainage":0.0,"lawn_interception":1.0,"lawn_Kcb":0.9,"lawn_Ke":0.06,"lawn_E":0.14,"lawn_T":0.55,"lawn_De":0.14,"lawn_few":0.05,"shrubs_theta":0.1862,"shrubs_depletion":12.5,"shrubs_ETc":2.27,"shrubs_Kc":0.95,"shrubs_irrigation":0,"shrubs_drainage":0.0,"shrubs_interception":1.5,"shrubs_Kcb":0.83,"shrubs_Ke":0.12,"shrubs_E":0.29,"shrubs_T":1.98,"shrubs_De":0.29,"shrubs_few":0.1},{"date":"2026-06-03","Tmax":18.8,"Tmin":13.9,"Tmean":15.9,"RHmean":81,"u2":4.38382435723434,"Rs":20.03,"precip":8.4,"ET0_om":3.19,"precip_prob":87,"era5_theta_lawn":0.6993,"era5_theta_shrubs":0.7044,"forecast":true,"partial_factor":1.0,"ET0":3.23,"lawn_theta":0.2,"lawn_depletion":0.0,"lawn_ETc":3.1,"lawn_Kc":0.96,"lawn_irrigation":0,"lawn_drainage":3.18,"lawn_interception":1.0,"lawn_Kcb":0.9,"lawn_Ke":0.06,"lawn_E":0.19,"lawn_T":2.91,"lawn_De":0.19,"lawn_few":0.05,"shrubs_theta":0.1939,"shrubs_depletion":5.5,"shrubs_ETc":3.07,"shrubs_Kc":0.95,"shrubs_irrigation":0,"shrubs_drainage":0.0,"shrubs_interception":1.49,"shrubs_Kcb":0.83,"shrubs_Ke":0.12,"shrubs_E":0.39,"shrubs_T":2.68,"shrubs_De":0.39,"shrubs_few":0.1}],"irrigations":{"2026-04-22_lawn":17,"2026-04-22_shrubs":12,"2026-04-25_lawn":3.3,"2026-04-26_lawn":3.3,"2026-04-26_shrubs":0.3,"2026-04-29_lawn":6.7,"2026-04-29_shrubs":14,"_meta":{"2026-04-22":{"minLawn":51,"mmLawn":17,"minShrubs":360,"mmShrubs":12},"2026-04-25":{"minLawn":10,"mmLawn":3.3,"minShrubs":0,"mmShrubs":0},"2026-04-26":{"minLawn":10,"mmLawn":3.3,"minShrubs":10,"mmShrubs":0.3},"2026-04-29":{"minLawn":20,"mmLawn":6.7,"minShrubs":420,"mmShrubs":14},"2026-04-30":{"minLawn":23,"mmLawn":7.7,"minShrubs":23,"mmShrubs":0.8},"2026-05-06":{"minLawn":0,"mmLawn":0,"minShrubs":480,"mmShrubs":16},"2026-05-08":{"minLawn":35,"mmLawn":11.7,"minShrubs":35,"mmShrubs":1.2},"2026-05-17":{"minLawn":0,"mmLawn":0,"minShrubs":435,"mmShrubs":14.5},"2026-05-23":{"minLawn":5,"mmLawn":1.7,"minShrubs":40,"mmShrubs":1.3},"2026-05-25":{"minLawn":45,"mmLawn":15,"minShrubs":0,"mmShrubs":0},"2026-05-27":{"minLawn":0,"mmLawn":0,"minShrubs":1500,"mmShrubs":50},"2026-05-28":{"minLawn":35,"mmLawn":11.7,"minShrubs":50,"mmShrubs":1.7}},"2026-04-30_lawn":7.7,"2026-04-30_shrubs":0.8,"2026-05-06_shrubs":16,"2026-05-08_lawn":11.7,"2026-05-08_shrubs":1.2,"2026-05-17_shrubs":14.5,"2026-05-23_lawn":1.7,"2026-05-23_shrubs":1.3,"2026-05-25_lawn":15,"2026-05-27_shrubs":50,"2026-05-28_lawn":11.7,"2026-05-28_shrubs":1.7},"monthly_totals":{"2025-03":{"rain":4.9,"irrigation":0.0,"ETc_lawn":13.5,"ETc_shrubs":14.2},"2025-04":{"rain":43.4,"irrigation":0.0,"ETc_lawn":28.9,"ETc_shrubs":37.5},"2025-05":{"rain":63.7,"irrigation":0.0,"ETc_lawn":25.2,"ETc_shrubs":42.2},"2025-06":{"rain":50.8,"irrigation":0.0,"ETc_lawn":53.3,"ETc_shrubs":76.4},"2025-07":{"rain":84.0,"irrigation":0.0,"ETc_lawn":77.5,"ETc_shrubs":71.8},"2025-08":{"rain":23.4,"irrigation":0.0,"ETc_lawn":25.5,"ETc_shrubs":38.5},"2025-09":{"rain":84.6,"irrigation":0.0,"ETc_lawn":50.7,"ETc_shrubs":42.2},"2025-10":{"rain":135.0,"irrigation":0.0,"ETc_lawn":21.1,"ETc_shrubs":19.7},"2025-11":{"rain":77.9,"irrigation":0.0,"ETc_lawn":5.9,"ETc_shrubs":5.1},"2025-12":{"rain":23.7,"irrigation":0.0,"ETc_lawn":3.2,"ETc_shrubs":2.5},"2026-01":{"rain":79.4,"irrigation":0.0,"ETc_lawn":0.5,"ETc_shrubs":0.4},"2026-02":{"rain":61.0,"irrigation":0.0,"ETc_lawn":3.5,"ETc_shrubs":2.6},"2026-03":{"rain":52.8,"irrigation":0.0,"ETc_lawn":19.4,"ETc_shrubs":14.8},"2026-04":{"rain":3.5,"irrigation":65.1,"ETc_lawn":38.7,"ETc_shrubs":41.2}},"lawn_status":{"state":"wet","priority":"none","depletion_pct":19.1,"deficit_mm":4.2,"days_to_stress":2,"rain7_mm":29.1,"eff_rain_3d_mm":0.04,"eff_rain_7d_mm":21.86,"eff_rain_intercepted_7d_mm":2.46,"proposal_mm":0,"proposal_min":0},"shrubs_status":{"state":"wet","priority":"none","depletion_pct":6.3,"deficit_mm":3.5,"days_to_stress":null,"rain7_mm":29.1,"eff_rain_3d_mm":0.03,"eff_rain_7d_mm":20.86,"eff_rain_intercepted_7d_mm":3.47,"proposal_mm":0,"proposal_min":0}}